versy/__init__.py
versy/__main__.py
versy/changelog.py
versy/git.py
versy/semver.py
versy/version_file.py
versy/versy.py
versy-1.0.2.data/scripts/versy
versy-1.0.2.dist-info/LICENSE
versy-1.0.2.dist-info/METADATA
versy-1.0.2.dist-info/WHEEL
versy-1.0.2.dist-info/top_level.txt
versy-1.0.2.dist-info/RECORD
